NoobStuffs/__init__.py
NoobStuffs/libandroid/__init__.py
NoobStuffs/libdatetime/__init__.py
NoobStuffs/libenvconfig/__init__.py
NoobStuffs/libformatter/__init__.py
NoobStuffs/libformatter/escape.py
NoobStuffs/libgithub/__init__.py
NoobStuffs/liblogging/__init__.py
NoobStuffs/libpasty/__init__.py
NoobStuffs/libtelegrambot/__init__.py
NoobStuffs/libtelegraph/__init__.py
NoobStuffs/libyamlconfig/__init__.py
noobstuffs-2.0.9.dist-info/METADATA
noobstuffs-2.0.9.dist-info/WHEEL
noobstuffs-2.0.9.dist-info/RECORD
