Metadata-Version: 2.1
Name: NoobStuffs
Version: 2.0.9
Summary: Python Library for PrajjuS Projects
Home-page: https://github.com/PrajjuS/NoobStuffs
License: GPL-3.0
Keywords: noobstuffs,libs,noob,lazy
Author: PrajjuS
Author-email: theprajjus@gmail.com
Requires-Python: >=3.8,<4.0
Classifier: License :: OSI Approved :: GNU General Public License v3 (GPLv3)
Classifier: Operating System :: OS Independent
Classifier: Programming Language :: Python :: 3
Classifier: Programming Language :: Python :: 3.8
Classifier: Programming Language :: Python :: 3.9
Classifier: Programming Language :: Python :: 3.10
Classifier: Programming Language :: Python :: 3.11
Classifier: Programming Language :: Python :: 3.12
Classifier: Programming Language :: Python :: 3.13
Requires-Dist: PyGithub (>=1.55,<3.0)
Requires-Dist: python-telegram-bot (>=21.0.1,<22.0.0)
Requires-Dist: pytz (>=2022.1,<2025.0)
Requires-Dist: pyyaml (>=6.0.2,<7.0.0)
Requires-Dist: requests (>=2.28.0,<3.0.0)
Requires-Dist: telegraph (>=2.2.0,<3.0.0)
